cynes/__init__.py
cynes/emulator.cpython-39-x86_64-linux-gnu.so
cynes/emulator.pyi
cynes/windowed.py
cynes.libs/libgcc_s-0cd532bd.so.1
cynes.libs/libstdc++-5d72f927.so.6.0.33
cynes-0.1.1.dist-info/METADATA
cynes-0.1.1.dist-info/WHEEL
cynes-0.1.1.dist-info/top_level.txt
cynes-0.1.1.dist-info/RECORD
cynes-0.1.1.dist-info/licenses/LICENSE
