Metadata-Version: 2.4
Name: cynes
Version: 0.1.1
Summary: C/C++ NES emulator with Python bindings
Author-email: Theo Combey <combey.theo@hotmail.com>
License-Expression: MIT
Project-URL: Homepage, https://github.com/Youlixx/cynes
Classifier: Development Status :: 4 - Beta
Classifier: Operating System :: MacOS
Classifier: Operating System :: Microsoft :: Windows
Classifier: Operating System :: Unix
Classifier: Programming Language :: Python :: 3.9
Classifier: Programming Language :: Python :: 3.10
Classifier: Programming Language :: Python :: 3.11
Classifier: Programming Language :: Python :: 3.12
Classifier: Programming Language :: Python :: 3.13
Classifier: Programming Language :: Python :: 3.14
Requires-Python: >=3.9
License-File: LICENSE
Requires-Dist: numpy
Dynamic: license-file
